sqlite_utils_sqlite_lines/__init__.py
sqlite_utils_sqlite_lines/version.py
sqlite_utils_sqlite_lines-0.2.2.dist-info/METADATA
sqlite_utils_sqlite_lines-0.2.2.dist-info/WHEEL
sqlite_utils_sqlite_lines-0.2.2.dist-info/entry_points.txt
sqlite_utils_sqlite_lines-0.2.2.dist-info/top_level.txt
sqlite_utils_sqlite_lines-0.2.2.dist-info/RECORD
