Metadata-Version: 2.1
Name: sqlite-utils-sqlite-lines
Version: 0.2.2
Summary: TODO
Author: Alex Garcia
License: Apache-2.0
Project-URL: Homepage, https://github.com/asg017/sqlite-lines
Project-URL: Changelog, https://github.com/asg017/sqlite-lines/releases
Project-URL: Issues, https://github.com/asg017/sqlite-lines/issues
Requires-Dist: sqlite-utils
Requires-Dist: sqlite-lines
